{
  "data": {
    "cheeseFans": [
      {
        "title": "Darth",
        "last_name": "Hagenes",
        "favorite_cheese": "brie",
        "favorite_wine": "strawwberrry_wine"
      },
      {
        "title": "Ms.",
        "last_name": "McClure",
        "favorite_cheese": "paneer",
        "favorite_wine": "pinot_grigio"
      },
      {
        "title": "Dr.",
        "last_name": "Bauch",
        "favorite_cheese": "cheez_whiz",
        "favorite_wine": "strawwberrry_wine"
      },
      {
        "title": "Miss",
        "last_name": "Fadel",
        "favorite_cheese": "brie",
        "favorite_wine": "merlot"
      },
      {
        "title": "Ms.",
        "last_name": "Walker",
        "favorite_cheese": "muenster",
        "favorite_wine": "strawwberrry_wine"
      }
    ]
  }
}